django_ninja_shield/__init__.py
django_ninja_shield/base.py
django_ninja_shield/decorators.py
django_ninja_shield/py.typed
django_ninja_shield-0.0.8.dist-info/METADATA
django_ninja_shield-0.0.8.dist-info/WHEEL
django_ninja_shield-0.0.8.dist-info/RECORD
