Metadata-Version: 2.4
Name: django-ninja-shield
Version: 0.0.8
Summary: A python package to control permissions for django ninja.
License: MIT
Keywords: django,django-ninja,permissions,shield,ninja permissions
Author: medram
Author-email: mramouchy@gmail.com
Requires-Python: >=3.10,<4.0
Classifier: License :: OSI Approved :: MIT License
Classifier: Programming Language :: Python :: 3
Classifier: Programming Language :: Python :: 3.10
Classifier: Programming Language :: Python :: 3.11
Classifier: Programming Language :: Python :: 3.12
Classifier: Programming Language :: Python :: 3.13
Classifier: Programming Language :: Python :: 3.14
Requires-Dist: django (>=4.0,<6.0)
Project-URL: Documentation, https://github.com/medram/django-ninja-shield
Project-URL: Homepage, https://github.com/medram/django-ninja-shield
Project-URL: Repository, https://github.com/medram/django-ninja-shield
